{
    "package_info": {
        "name": "HelloWorld",
        "version": "1.0.0",
        "package_date": "2025-06-30 19:30:55",
        "package_size": 14046,
        "package_format": "zip"
    },
    "plugin_info": {
        "name": "HelloWorld",
        "version": "1.0.0",
        "description": "A simple hello world plugin for Shopologic",
        "author": {
            "name": "Shopologic Team"
        },
        "requirements": {
            "php": ">=8.3",
            "core": ">=1.0.0"
        },
        "bootstrap": {
            "class": "HelloWorldPlugin",
            "file": "HelloWorldPlugin.php"
        },
        "permissions": [
            "hooks.*",
            "events.*",
            "cache.access",
            "config.*",
            "routes.register",
            "log.write"
        ],
        "autoload": {
            "psr-4": {
                "Shopologic\\Plugins\\HelloWorld\\": "src\/"
            }
        }
    },
    "marketplace_info": {
        "category": "general",
        "tags": [
            "general"
        ],
        "compatibility": {
            "php": ">=8.3",
            "shopologic": ">=2.0"
        },
        "pricing": {
            "model": "free",
            "price": 0
        }
    },
    "quality_metrics": {
        "health_score": 0,
        "performance_grade": "A",
        "test_coverage": 40,
        "security_score": 100
    },
    "assets": {
        "icon": "marketplace-assets\/icon.svg",
        "banner": "marketplace-assets\/banner.svg",
        "logo": "marketplace-assets\/logo.svg",
        "screenshots": [
            "marketplace-assets\/screenshots\/screenshot-1.svg",
            "marketplace-assets\/screenshots\/screenshot-2.svg",
            "marketplace-assets\/screenshots\/screenshot-3.svg"
        ]
    }
}